etna_cli/__init__.py
etna_cli/activity.py
etna_cli/config.py
etna_cli/conversation.py
etna_cli/declaration.py
etna_cli/etna.py
etna_cli/etna_gitlab.py
etna_cli/event.py
etna_cli/project.py
etna_cli/rank.py
etna_cli/student.py
etna_cli/task.py
etna_cli/ticket.py
etna_cli/utils.py
etna_cli-0.8.0.dist-info/entry_points.txt
etna_cli-0.8.0.dist-info/LICENSE
etna_cli-0.8.0.dist-info/WHEEL
etna_cli-0.8.0.dist-info/METADATA
etna_cli-0.8.0.dist-info/RECORD
