Metadata-Version: 2.1
Name: etna-cli
Version: 0.8.0
Summary: Command line tool for my school's intranet
Home-page: https://github.com/matteyeux/etna
License: MIT
Keywords: etna
Author: matteyeux
Requires-Python: >=3.7,<4.0
Classifier: Development Status :: 4 - Beta
Classifier: Intended Audience :: Developers
Classifier: Intended Audience :: Education
Classifier: Intended Audience :: System Administrators
Classifier: License :: OSI Approved :: MIT License
Classifier: Programming Language :: Python :: 3
Classifier: Programming Language :: Python :: 3.6
Classifier: Programming Language :: Python :: 3.7
Classifier: Programming Language :: Python :: 3.8
Classifier: Programming Language :: Python :: 3.9
Classifier: Topic :: Utilities
Requires-Dist: click (>=7.0,<8.0)
Requires-Dist: click-default-group (>=1.2.2,<2.0.0)
Requires-Dist: etnawrapper (>=2.5.0,<3.0.0)
Requires-Dist: keyring (>=21.1.0,<22.0.0)
Requires-Dist: pendulum (>=2.0.5,<3.0.0)
Requires-Dist: python-gitlab (>=2.0.1,<3.0.0)
Requires-Dist: tabulate (>=0.8.7,<0.9.0)
Requires-Dist: taskw (>=1.2.0,<2.0.0)
Project-URL: Repository, https://github.com/matteyeux/etna
